{
	"info": {
		"_postman_id": "d3e1d689-e2c9-43e7-9776-2804e03ac47b",
		"name": "order-processor",
		"schema": "https://schema.getpostman.com/json/collection/v2.1.0/collection.json",
		"_exporter_id": "13208461",
		"_collection_link": "https://martian-comet-116084.postman.co/workspace/MyWorkspace~9282dfdf-f756-45bf-9ded-4285e40ff1b4/collection/13208461-d3e1d689-e2c9-43e7-9776-2804e03ac47b?action=share&source=collection_link&creator=13208461"
	},
	"item": [
		{
			"name": "getOrder",
			"request": {
				"auth": {
					"type": "noauth"
				},
				"method": "GET",
				"header": [
					{
						"key": "Authorization",
						"value": "Bearer eyJhbGciOiJIUzI1NiIsInR5cCI6IkpXVCJ9.eyJzZWxsZXJJZCI6IjY2MDgxMDg0OGE3NTRlMGMzMmQ2Y2EyYSJ9.Me30gMGf-T15zr6FoPRLc6QnPT2KDn7JFA4Rg0Jte0c",
						"type": "text"
					}
				],
				"url": {
					"raw": "localhost:8080/api/v1/orders?startDate=31/03/2024&endDate=31/03/2024&orderStatus=FINISHED&paymentMethod=CREDIT&paymentStatus=refused",
					"host": [
						"localhost"
					],
					"port": "8080",
					"path": [
						"api",
						"v1",
						"orders"
					],
					"query": [
						{
							"key": "startDate",
							"value": "31/03/2024"
						},
						{
							"key": "endDate",
							"value": "31/03/2024"
						},
						{
							"key": "orderStatus",
							"value": "FINISHED"
						},
						{
							"key": "paymentMethod",
							"value": "CREDIT"
						},
						{
							"key": "paymentStatus",
							"value": "refused"
						}
					]
				}
			},
			"response": []
		}
	]
}